CHANGELOG.txt
LICENCE.txt
MANIFEST.in
README.txt
setup.py
matching_function/__init__.py
reg_sieves.egg-info/PKG-INFO
reg_sieves.egg-info/SOURCES.txt
reg_sieves.egg-info/dependency_links.txt
reg_sieves.egg-info/requires.txt
reg_sieves.egg-info/top_level.txt