Metadata-Version: 1.1
Name: reg-sieves
Version: 0.0.1
Summary: The regression approach with sieves.
Home-page: UNKNOWN
Author: Anzony Quispe
Author-email: anzony.quispe@gmail.com
License: MIT
Keywords: sieves
Platform: UNKNOWN
Classifier: Development Status :: 5 - Production/Stable
Classifier: Intended Audience :: Education
Classifier: Operating System :: Microsoft :: Windows :: Windows 10
Classifier: License :: OSI Approved :: MIT License
Classifier: Programming Language :: Python :: 3
